uasiren/__init__.py
uasiren/client.py
uasiren-0.0.1.dist-info/METADATA
uasiren-0.0.1.dist-info/WHEEL
uasiren-0.0.1.dist-info/top_level.txt
uasiren-0.0.1.dist-info/RECORD
