Metadata-Version: 2.1
Name: uasiren
Version: 0.0.1
Summary: Implements siren.pp.ua API - public wrapper for api.ukrainealarm.com API that returns info about Ukraine air-raid alarms.
Home-page: https://github.com/PaulAnnekov/uasiren
Author: Pavlo Annekov
Author-email: paul.annekov@gmail.com
License: MIT
Classifier: Programming Language :: Python :: 3
Classifier: License :: OSI Approved :: MIT License
Classifier: Operating System :: OS Independent
